dbt_platform_helper/COMMANDS.md
dbt_platform_helper/README.md
dbt_platform_helper/__init__.py
dbt_platform_helper/commands/__init__.py
dbt_platform_helper/commands/application.py
dbt_platform_helper/commands/codebase.py
dbt_platform_helper/commands/conduit.py
dbt_platform_helper/commands/config.py
dbt_platform_helper/commands/copilot.py
dbt_platform_helper/commands/database.py
dbt_platform_helper/commands/environment.py
dbt_platform_helper/commands/generate.py
dbt_platform_helper/commands/internal.py
dbt_platform_helper/commands/notify.py
dbt_platform_helper/commands/pipeline.py
dbt_platform_helper/commands/secrets.py
dbt_platform_helper/commands/version.py
dbt_platform_helper/constants.py
dbt_platform_helper/default-extensions.yml
dbt_platform_helper/domain/__init__.py
dbt_platform_helper/domain/codebase.py
dbt_platform_helper/domain/conduit.py
dbt_platform_helper/domain/config.py
dbt_platform_helper/domain/copilot.py
dbt_platform_helper/domain/copilot_environment.py
dbt_platform_helper/domain/database_copy.py
dbt_platform_helper/domain/maintenance_page.py
dbt_platform_helper/domain/notify.py
dbt_platform_helper/domain/pipelines.py
dbt_platform_helper/domain/plans.py
dbt_platform_helper/domain/secrets.py
dbt_platform_helper/domain/service.py
dbt_platform_helper/domain/terraform_environment.py
dbt_platform_helper/domain/update_alb_rules.py
dbt_platform_helper/domain/versioning.py
dbt_platform_helper/entities/platform_config_schema.py
dbt_platform_helper/entities/semantic_version.py
dbt_platform_helper/entities/service.py
dbt_platform_helper/jinja2_tags.py
dbt_platform_helper/platform_exception.py
dbt_platform_helper/providers/__init__.py
dbt_platform_helper/providers/autoscaling.py
dbt_platform_helper/providers/aws/__init__.py
dbt_platform_helper/providers/aws/exceptions.py
dbt_platform_helper/providers/aws/interfaces.py
dbt_platform_helper/providers/aws/opensearch.py
dbt_platform_helper/providers/aws/redis.py
dbt_platform_helper/providers/aws/sso_auth.py
dbt_platform_helper-15.18.0.dist-info/METADATA
dbt_platform_helper-15.18.0.dist-info/WHEEL
dbt_platform_helper-15.18.0.dist-info/entry_points.txt
dbt_platform_helper-15.18.0.dist-info/licenses/LICENSE
dbt_platform_helper-15.18.0.dist-info/RECORD
