Metadata-Version: 2.4
Name: dbt-platform-helper
Version: 15.18.0
Summary: Set of tools to help transfer applications/services from GOV.UK PaaS to DBT PaaS augmenting AWS Copilot.
License: MIT
License-File: LICENSE
Author: Department for Business and Trade Platform Team
Author-email: sre-team@digital.trade.gov.uk
Requires-Python: >3.10.0,<4.0
Classifier: License :: OSI Approved :: MIT License
Classifier: Programming Language :: Python :: 3
Classifier: Programming Language :: Python :: 3.11
Classifier: Programming Language :: Python :: 3.12
Classifier: Programming Language :: Python :: 3.13
Classifier: Programming Language :: Python :: 3.14
Requires-Dist: Jinja2 (==3.1.6)
Requires-Dist: boto3 (>=1.35.2,<2.0.0)
Requires-Dist: botocore (>=1.34.85,<2.0.0)
Requires-Dist: cfn-flip (>=1.3.0,<2.0.0)
Requires-Dist: click (>=8.1.3,<9.0.0)
Requires-Dist: jinja2-simple-tags (>=0.5,<0.7)
Requires-Dist: prettytable (>=3.9.0,<4.0.0)
Requires-Dist: psycopg2-binary (>=2.9.9,<3.0.0)
Requires-Dist: pydantic (>=2.11.7,<3.0.0)
Requires-Dist: requests (>=2.31.0,<3.0.0)
Requires-Dist: schema (==0.7.8)
Requires-Dist: slack-sdk (>=3.27.1,<4.0.0)
Requires-Dist: yamllint (>=1.35.1,<2.0.0)
